universo/__init__.py
universo/db.py
caverimx_db-0.1.1.dist-info/LICENCE
caverimx_db-0.1.1.dist-info/METADATA
caverimx_db-0.1.1.dist-info/WHEEL
caverimx_db-0.1.1.dist-info/top_level.txt
caverimx_db-0.1.1.dist-info/RECORD
