Metadata-Version: 2.1
Name: caverimx-db
Version: 0.1.1
Summary: A small file system based database package
Home-page: https://gitlab.com/caverimx/caverimx-db.git
Author: Alexis Betancourt
Author-email: alexis@caveri.mx
License: UNKNOWN
Platform: UNKNOWN
Classifier: Programming Language :: Python :: 3
Classifier: License :: OSI Approved :: MIT License
Classifier: Operating System :: OS Independent
Requires-Python: >=3.6
